fractals_cli/__init__.py
fractals_cli/cli.py
fractals_cli-0.0.1.dist-info/LICENSE
fractals_cli-0.0.1.dist-info/METADATA
fractals_cli-0.0.1.dist-info/WHEEL
fractals_cli-0.0.1.dist-info/entry_points.txt
fractals_cli-0.0.1.dist-info/top_level.txt
fractals_cli-0.0.1.dist-info/RECORD
