Metadata-Version: 2.1
Name: fractals-cli
Version: 0.0.1
Summary: [Under Construction] Print fractals to the console!
Author-email: Spiro Metaxas <spirometaxas@outlook.com>
Maintainer-email: Spiro Metaxas <spirometaxas@outlook.com>
License: MIT License
Project-URL: Homepage, https://spirometaxas.com/projects/fractals-cli/
Project-URL: Repository, https://github.com/spirometaxas/fractals-cli-py
Keywords: Fractals
Classifier: Development Status :: 4 - Beta
Classifier: License :: OSI Approved :: MIT License
Classifier: Programming Language :: Python
Classifier: Programming Language :: Python :: 3.12
Classifier: Programming Language :: Python :: 3.11
Classifier: Programming Language :: Python :: 3.10
Classifier: Programming Language :: Python :: 3.9
Classifier: Programming Language :: Python :: 3.8
Classifier: Programming Language :: Python :: 3
Classifier: Operating System :: OS Independent
Requires-Python: >=3.8
License-File: LICENSE
